squarify/__init__.py
squarify-0.4.4.dist-info/LICENSE.txt
squarify-0.4.4.dist-info/METADATA
squarify-0.4.4.dist-info/WHEEL
squarify-0.4.4.dist-info/top_level.txt
squarify-0.4.4.dist-info/RECORD
